aiohttp_rest_framework/__init__.py
aiohttp_rest_framework/exceptions.py
aiohttp_rest_framework/fields.py
aiohttp_rest_framework/mixins.py
aiohttp_rest_framework/serializers.py
aiohttp_rest_framework/settings.py
aiohttp_rest_framework/types.py
aiohttp_rest_framework/utils.py
aiohttp_rest_framework/views.py
aiohttp_rest_framework/db/__init__.py
aiohttp_rest_framework/db/base.py
aiohttp_rest_framework/db/sa.py
aiohttp_rest_framework-0.0.6.dist-info/LICENCE
aiohttp_rest_framework-0.0.6.dist-info/METADATA
aiohttp_rest_framework-0.0.6.dist-info/WHEEL
aiohttp_rest_framework-0.0.6.dist-info/top_level.txt
aiohttp_rest_framework-0.0.6.dist-info/RECORD
