Metadata-Version: 2.1
Name: aiohttp-rest-framework
Version: 0.0.6
Summary: Rest framework for aiohttp web server
Home-page: https://github.com/ckkz-it/aiohttp-rest-framework
Author: Andrey Laguta
Author-email: cirkus.kz@gmail.com
License: MIT
Keywords: restframework rest_framework aiohttp serializers asyncio rest aiohttp_rest_framework
Platform: UNKNOWN
Classifier: Development Status :: 3 - Alpha
Classifier: Environment :: Web Environment
Classifier: Framework :: AsyncIO
Classifier: Intended Audience :: Developers
Classifier: Operating System :: OS Independent
Classifier: Programming Language :: Python :: 3.6
Classifier: Programming Language :: Python :: 3.7
Classifier: Programming Language :: Python :: 3.8
Classifier: Programming Language :: Python :: 3.9
Classifier: Topic :: Internet :: WWW/HTTP
Classifier: License :: OSI Approved :: MIT License
Requires-Python: >=3.6
Requires-Dist: aiohttp
Requires-Dist: marshmallow
Requires-Dist: SQLAlchemy (==1.4.0b1)
Requires-Dist: psycopg2
Requires-Dist: asyncpg
